google/cloud/bigquery_datatransfer/__init__.py
google/cloud/bigquery_datatransfer/gapic_version.py
google/cloud/bigquery_datatransfer/py.typed
google/cloud/bigquery_datatransfer_v1/__init__.py
google/cloud/bigquery_datatransfer_v1/gapic_metadata.json
google/cloud/bigquery_datatransfer_v1/gapic_version.py
google/cloud/bigquery_datatransfer_v1/py.typed
google/cloud/bigquery_datatransfer_v1/services/__init__.py
google/cloud/bigquery_datatransfer_v1/services/data_transfer_service/__init__.py
google/cloud/bigquery_datatransfer_v1/services/data_transfer_service/async_client.py
google/cloud/bigquery_datatransfer_v1/services/data_transfer_service/client.py
google/cloud/bigquery_datatransfer_v1/services/data_transfer_service/pagers.py
google/cloud/bigquery_datatransfer_v1/services/data_transfer_service/transports/__init__.py
google/cloud/bigquery_datatransfer_v1/services/data_transfer_service/transports/base.py
google/cloud/bigquery_datatransfer_v1/services/data_transfer_service/transports/grpc.py
google/cloud/bigquery_datatransfer_v1/services/data_transfer_service/transports/grpc_asyncio.py
google/cloud/bigquery_datatransfer_v1/services/data_transfer_service/transports/rest.py
google/cloud/bigquery_datatransfer_v1/services/data_transfer_service/transports/rest_base.py
google/cloud/bigquery_datatransfer_v1/types/__init__.py
google/cloud/bigquery_datatransfer_v1/types/datatransfer.py
google/cloud/bigquery_datatransfer_v1/types/transfer.py
google_cloud_bigquery_datatransfer-3.19.1.dist-info/LICENSE
google_cloud_bigquery_datatransfer-3.19.1.dist-info/METADATA
google_cloud_bigquery_datatransfer-3.19.1.dist-info/WHEEL
google_cloud_bigquery_datatransfer-3.19.1.dist-info/top_level.txt
google_cloud_bigquery_datatransfer-3.19.1.dist-info/RECORD
